setup.py
src/allinux/__init__.py
src/allinux/shbuiltins.py
src/allinux/test_shbuiltins.py
src/allinux.egg-info/PKG-INFO
src/allinux.egg-info/SOURCES.txt
src/allinux.egg-info/dependency_links.txt
src/allinux.egg-info/top_level.txt
src/allinux/coreutils/__init__.py
src/allinux/coreutils/basic_operations.py
src/allinux/coreutils/coreutils.py
src/allinux/coreutils/system_context.py
src/allinux/coreutils/test_coreutils.py
src/allinux/coreutils/test_system_context.py