Metadata-Version: 1.1
Name: allinux
Version: 0.2.0
Summary: Linux command collections
Home-page: https://github.com/andrewliqw/python-linux-command
Author: Andrew Li
Author-email: andrewliqw@outlook.com
License: MIT
Keywords: python linux command
Platform: UNKNOWN
Classifier: Development Status :: 2 - Pre-Alpha
Classifier: Programming Language :: Python :: 3.5
